aiomysensors/__init__.py
aiomysensors/__main__.py
aiomysensors/exceptions.py
aiomysensors/gateway.py
aiomysensors/persistence.py
aiomysensors/py.typed
aiomysensors/cli/__init__.py
aiomysensors/cli/helper.py
aiomysensors/model/__init__.py
aiomysensors/model/const.py
aiomysensors/model/message.py
aiomysensors/model/node.py
aiomysensors/model/protocol/__init__.py
aiomysensors/model/protocol/message_handler.py
aiomysensors/model/protocol/protocol_14.py
aiomysensors/model/protocol/protocol_15.py
aiomysensors/model/protocol/protocol_20.py
aiomysensors/model/protocol/protocol_21.py
aiomysensors/model/protocol/protocol_22.py
aiomysensors/transport/__init__.py
aiomysensors/transport/mqtt.py
aiomysensors/transport/serial.py
aiomysensors/transport/tcp.py
aiomysensors-0.11.0.dist-info/licenses/LICENSE
aiomysensors-0.11.0.dist-info/METADATA
aiomysensors-0.11.0.dist-info/WHEEL
aiomysensors-0.11.0.dist-info/entry_points.txt
aiomysensors-0.11.0.dist-info/top_level.txt
aiomysensors-0.11.0.dist-info/RECORD
