Metadata-Version: 2.4
Name: aiomysensors
Version: 0.11.0
Summary: Python asyncio package to connect to MySensors gateways.
Author-email: Martin Hjelmare <marhje52@gmail.com>
License: Apache-2.0
Project-URL: Bug Tracker, https://github.com/MartinHjelmare/aiomysensors/issues
Project-URL: Changelog, https://github.com/MartinHjelmare/aiomysensors/blob/main/CHANGELOG.md
Project-URL: repository, https://github.com/MartinHjelmare/aiomysensors
Classifier: Development Status :: 3 - Alpha
Classifier: Intended Audience :: Developers
Classifier: Natural Language :: English
Classifier: Operating System :: OS Independent
Classifier: Programming Language :: Python :: 3.12
Classifier: Programming Language :: Python :: 3.13
Classifier: Topic :: Software Development :: Libraries
Classifier: Topic :: Home Automation
Requires-Python: >=3.12
License-File: LICENSE
Requires-Dist: aiofiles<25,>=24
Requires-Dist: awesomeversion<26,>=25
Requires-Dist: mashumaro>=3.15
Requires-Dist: pyserial-asyncio-fast>=0.16
Provides-Extra: cli
Requires-Dist: aiomqtt<3,>=2.3; extra == "cli"
Requires-Dist: typer<1,>=0.15; extra == "cli"
Dynamic: license-file
